sample_momo/__init__.py
sample_momo/momo.py
sample_momo-0.1.1.dist-info/METADATA
sample_momo-0.1.1.dist-info/WHEEL
sample_momo-0.1.1.dist-info/RECORD
