Metadata-Version: 2.1
Name: sample-momo
Version: 0.1.1
Summary: 
Author: nekonekko
Author-email: momoichigodayo+github@gmail.com
Requires-Python: >=3.12,<4.0
Classifier: Programming Language :: Python :: 3
Classifier: Programming Language :: Python :: 3.12
Requires-Dist: anndata (>=0.10.9,<0.11.0)
Requires-Dist: numpy (>=2.1.1,<3.0.0)
Requires-Dist: pandas (>=2.2.3,<3.0.0)
